aiofb/__init__.py
aiofb/api.py
aiofb/exceptions.py
aiofb-0.1.1.dist-info/DESCRIPTION.rst
aiofb-0.1.1.dist-info/METADATA
aiofb-0.1.1.dist-info/RECORD
aiofb-0.1.1.dist-info/WHEEL
aiofb-0.1.1.dist-info/metadata.json
aiofb-0.1.1.dist-info/top_level.txt
