Metadata-Version: 2.0
Name: aiofb
Version: 0.1.1
Summary: Asyncio Python client for Facebook API
Home-page: https://github.com/tehamalab/aiofb
Author: Tehamalab
Author-email: developers@tehamalab.com
License: BSD license
Keywords: aiofb
Platform: UNKNOWN
Classifier: Development Status :: 2 - Pre-Alpha
Classifier: Intended Audience :: Developers
Classifier: License :: OSI Approved :: BSD License
Classifier: Natural Language :: English
Classifier: Programming Language :: Python :: 3
Classifier: Programming Language :: Python :: 3.5
Classifier: Programming Language :: Python :: 3.6
Requires-Dist: aiohttp
